bcml-3.10.8.dist-info/METADATA
bcml-3.10.8.dist-info/WHEEL
bcml-3.10.8.dist-info/entry_points.txt
bcml-3.10.8.dist-info/license_files/LICENSE.md
bcml/util.py
bcml/install.py
bcml/__version__.py
bcml/data/logo.png
bcml/data/hashes/switch.sjson
bcml/data/hashes/msyts.sjson
bcml/data/hashes/wiiu.sjson
bcml/data/bcml.ico
bcml/data/gb.sjson
bcml/_oneclick.py
bcml/upgrade.py
bcml/_server.py
bcml/dev.py
bcml/helpers/7z.dll
bcml/helpers/7z.exe
bcml/helpers/__init__.py
bcml/helpers/7z
bcml/pickles.py
bcml/__init__.py
bcml/_api.py
bcml/assets/help/beware/index.html
bcml/assets/help/export/index.html
bcml/assets/help/trouble/index.html
bcml/assets/help/mods/index.html
bcml/assets/help/install/index.html
bcml/assets/help/index.html
bcml/assets/help/bnp/index.html
bcml/assets/help/license/pywebview/index.html
bcml/assets/help/license/msyt/index.html
bcml/assets/help/license/7z/index.html
bcml/assets/help/LICENSE/index.html
bcml/assets/help/sitemap.xml
bcml/assets/help/ui.png
bcml/assets/help/assets/images/favicon.png
bcml/assets/help/assets/javascripts/lunr/min/lunr.th.min.js
bcml/assets/help/assets/javascripts/lunr/min/lunr.ko.min.js
bcml/assets/help/assets/javascripts/lunr/min/lunr.de.min.js
bcml/assets/help/assets/javascripts/lunr/min/lunr.multi.min.js
bcml/assets/help/assets/javascripts/lunr/min/lunr.it.min.js
bcml/assets/help/assets/javascripts/lunr/min/lunr.stemmer.support.min.js
bcml/assets/help/assets/javascripts/lunr/min/lunr.ar.min.js
bcml/assets/help/assets/javascripts/lunr/min/lunr.hu.min.js
bcml/assets/help/assets/javascripts/lunr/min/lunr.du.min.js
bcml/assets/help/assets/javascripts/lunr/min/lunr.zh.min.js
bcml/assets/help/assets/javascripts/lunr/min/lunr.pt.min.js
bcml/assets/help/assets/javascripts/lunr/min/lunr.ro.min.js
bcml/assets/help/assets/javascripts/lunr/min/lunr.sv.min.js
bcml/assets/help/assets/javascripts/lunr/min/lunr.tr.min.js
bcml/assets/help/assets/javascripts/lunr/min/lunr.fi.min.js
bcml/assets/help/assets/javascripts/lunr/min/lunr.nl.min.js
bcml/assets/help/assets/javascripts/lunr/min/lunr.vi.min.js
bcml/assets/help/assets/javascripts/lunr/min/lunr.fr.min.js
bcml-3.10.8.dist-info/RECORD
