Metadata-Version: 2.1
Name: bcml
Version: 3.10.8
Classifier: Programming Language :: Rust
Classifier: Programming Language :: Python :: Implementation :: CPython
Classifier: Programming Language :: Python :: Implementation :: PyPy
Classifier: Development Status :: 5 - Production/Stable
Classifier: License :: OSI Approved :: GNU General Public License v3 or later (GPLv3+)
Classifier: Operating System :: OS Independent
Classifier: Programming Language :: Python :: 3 :: Only
Requires-Dist: botw-utils~=0.2.3
Requires-Dist: cefpython3~=66.1; platform_system == 'Windows'
Requires-Dist: oead~=1.2.6
Requires-Dist: packaging~=21.3
Requires-Dist: pythonnet~=3.0.1
Requires-Dist: PyQt5; platform_system == 'Linux'
Requires-Dist: pyqtwebengine~=5.15.2; platform_system == 'Linux'
Requires-Dist: pywebview==3.7.2
Requires-Dist: QtPy; platform_system == 'Linux'
Requires-Dist: requests~=2.27.1
Requires-Dist: rstb>=1.2.2
Requires-Dist: xxhash~=3.2
License-File: LICENSE.md
Summary: A mod manager for The Legend of Zelda: Breath of the Wild
Author: Caleb Smith
Requires-Python: >=3.7
Project-URL: homepage, https://gamebanana.com/tools/6624
Project-URL: repository, https://github.com/NiceneNerd/BCML
